<?xml version="1.0" encoding="utf-8"?>
<LanguageData>
  <!--The following translations were generated by https://www.deepl.com/-->
  <!-- EN: make bearskin tiles -->
  <MakeBearskinTile.label>machen Bärenfell Fliesen</MakeBearskinTile.label>
  <!-- EN: Cut bearskin to tiles for make floors. -->
  <MakeBearskinTile.description>Schneiden Sie Bärenfell zu Fliesen für Böden zu machen.</MakeBearskinTile.description>
  <!-- EN: Cutting leather. -->
  <MakeBearskinTile.jobString>Schneiden von Leder.</MakeBearskinTile.jobString>
  <!-- EN: make birdskin tiles -->
  <MakeBirdskinTile.label>Vogelfellfliesen machen</MakeBirdskinTile.label>
  <!-- EN: Cut birdskin to tiles for make floors. -->
  <MakeBirdskinTile.description>Schneiden Sie Vogelfell zu Fliesen für Böden machen.</MakeBirdskinTile.description>
  <MakeBirdskinTile.jobString>Schneiden von Leder.</MakeBirdskinTile.jobString>
  <!-- EN: make bluefur tiles -->
  <MakeBluefurTile.label>Blaupelz-Fliesen machen</MakeBluefurTile.label>
  <!-- EN: Cut bluefur to tiles for make floors. -->
  <MakeBluefurTile.description>Schneiden Sie bluefur zu Fliesen für Böden zu machen.</MakeBluefurTile.description>
  <MakeBluefurTile.jobString>Schneiden von Leder.</MakeBluefurTile.jobString>
  <!-- EN: make camelhide tiles -->
  <MakeCamelhideTile.label>camelhide Fliesen machen</MakeCamelhideTile.label>
  <!-- EN: Cut camelhide to tiles for make floors. -->
  <MakeCamelhideTile.description>Schneiden Sie camelhide zu Fliesen für Böden zu machen.</MakeCamelhideTile.description>
  <MakeCamelhideTile.jobString>Schneiden von Leder.</MakeCamelhideTile.jobString>
  <!-- EN: make carved leather -->
  <MakeCarvedLeather.label>geschnitztes Leder herstellen</MakeCarvedLeather.label>
  <!-- EN: Carve leather for make tiles. -->
  <MakeCarvedLeather.description>Carve Leder für Fliesen machen.</MakeCarvedLeather.description>
  <!-- EN: Carving leather. -->
  <MakeCarvedLeather.jobString>Schnitzen von Leder.</MakeCarvedLeather.jobString>
  <!-- EN: make lightleather tiles -->
  <MakeLightleatherTile.label>helllederne Fliesen machen</MakeLightleatherTile.label>
  <!-- EN: Cut lightleather to tiles for make floors. -->
  <MakeLightleatherTile.description>Schneiden Sie lightleather zu Fliesen für Böden machen.</MakeLightleatherTile.description>
  <MakeLightleatherTile.jobString>Schneiden von Leder.</MakeLightleatherTile.jobString>
  <!-- EN: make lizardskin tiles -->
  <MakeLizardskinTile.label>Echsenhaut Kacheln machen</MakeLizardskinTile.label>
  <!-- EN: Cut lizardskin to tiles for make floors. -->
  <MakeLizardskinTile.description>Schneiden Sie Eidechsenhaut zu Fliesen für Böden machen.</MakeLizardskinTile.description>
  <MakeLizardskinTile.jobString>Schneiden von Leder.</MakeLizardskinTile.jobString>
  <!-- EN: make painted stone tile -->
  <MakePaintedStone.label>bemalte Steinfliese machen</MakePaintedStone.label>
  <!-- EN: Painted stone for make floors. -->
  <MakePaintedStone.description>Gemalt Stein für Böden zu machen.</MakePaintedStone.description>
  <!-- EN: Painting stone. -->
  <MakePaintedStone.jobString>Malerei Stein.</MakePaintedStone.jobString>
  <!-- EN: make pantherafur tiles -->
  <MakePantherafurTile.label>Pantherafur-Kacheln machen</MakePantherafurTile.label>
  <!-- EN: Cut panthera fur to tiles for make floors. -->
  <MakePantherafurTile.description>Schneiden Sie Panthera Fell zu Fliesen für Böden machen.</MakePantherafurTile.description>
  <MakePantherafurTile.jobString>Schneiden von Leder.</MakePantherafurTile.jobString>
  <!-- EN: make pigskin tiles -->
  <MakePigskinTile.label>machen Schweinsleder Fliesen</MakePigskinTile.label>
  <!-- EN: Cut pigskin to tiles for make floors. -->
  <MakePigskinTile.description>Schneiden Sie Schweinsleder zu Fliesen für Böden zu machen.</MakePigskinTile.description>
  <MakePigskinTile.jobString>Schneiden von Leder.</MakePigskinTile.jobString>
  <!-- EN: make plainleather tiles -->
  <MakePlainleatherTile.label>Glattlederfliesen herstellen</MakePlainleatherTile.label>
  <!-- EN: Cut plainleather to tiles for make floors. -->
  <MakePlainleatherTile.description>Schneiden Sie plainleather zu Fliesen für Böden zu machen.</MakePlainleatherTile.description>
  <MakePlainleatherTile.jobString>Schneiden von Leder.</MakePlainleatherTile.jobString>
  <!-- EN: make rhinocerosleather tiles -->
  <MakeRhinocerosleatherTile.label>Rhinozeros-Leder-Fliesen machen</MakeRhinocerosleatherTile.label>
  <!-- EN: Cut rhinoceros leather to tiles for make floors. -->
  <MakeRhinocerosleatherTile.description>Schneiden Sie Rhinozeros Leder zu Fliesen für Böden zu machen.</MakeRhinocerosleatherTile.description>
  <MakeRhinocerosleatherTile.jobString>Schneiden von Leder.</MakeRhinocerosleatherTile.jobString>
  <!-- EN: make thrumbofur tiles -->
  <MakeThrumbofurTile.label>Thrumbofur Fliesen machen</MakeThrumbofurTile.label>
  <!-- EN: Cut thrumbofur to tiles for make floors. -->
  <MakeThrumbofurTile.description>Schneiden Sie thrumbofur zu Fliesen für Böden zu machen.</MakeThrumbofurTile.description>
  <MakeThrumbofurTile.jobString>Schneiden von Leder.</MakeThrumbofurTile.jobString>
  <!-- EN: make wood planks -->
  <MakeWoodPlanks.label>Holzplanken herstellen</MakeWoodPlanks.label>
  <!-- EN: Splitting logs to planks for make floors. -->
  <MakeWoodPlanks.description>Spalten von Baumstämmen zu Brettern für Fußböden machen.</MakeWoodPlanks.description>
  <!-- EN: Splitting logs. -->
  <MakeWoodPlanks.jobString>Splitting logs.</MakeWoodPlanks.jobString>
</LanguageData>
